mydumper2s3/__init__.py
mydumper2s3/delete_bucket.py
mydumper2s3/mydumper2s3.py
mydumper2s3/verify_dump.py
mydumper2s3-0.1.6.dist-info/entry_points.txt
mydumper2s3-0.1.6.dist-info/WHEEL
mydumper2s3-0.1.6.dist-info/METADATA
mydumper2s3-0.1.6.dist-info/RECORD
